{
    "/js/app.js": "/js/app.js",
    "/installer/js/app.js": "/installer/js/app.js",
    "/js/chunks/8d23749804d82c5c.js": "/js/chunks/8d23749804d82c5c.js",
    "/js/chunks/4681d5faed0ace04.js": "/js/chunks/4681d5faed0ace04.js",
    "/js/chunks/7974966f620156b1.js": "/js/chunks/7974966f620156b1.js",
    "/js/chunks/2c81eb4b89b6d8a4.js": "/js/chunks/2c81eb4b89b6d8a4.js",
    "/js/chunks/abea852a416e8ba5.js": "/js/chunks/abea852a416e8ba5.js",
    "/js/chunks/93155e6f837b7881.js": "/js/chunks/93155e6f837b7881.js",
    "/js/chunks/b3a902fa88407225.js": "/js/chunks/b3a902fa88407225.js",
    "/js/chunks/e3e950e2542591b5.js": "/js/chunks/e3e950e2542591b5.js",
    "/js/chunks/b8f24118c33ffe73.js": "/js/chunks/b8f24118c33ffe73.js",
    "/js/chunks/f8cacf666c9aed81.js": "/js/chunks/f8cacf666c9aed81.js",
    "/css/app.css": "/css/app.css",
    "/js/chunks/41562e887ea1c778.js": "/js/chunks/41562e887ea1c778.js",
    "/js/chunks/d93116ec39e470fd.js": "/js/chunks/d93116ec39e470fd.js",
    "/js/chunks/a9a0d461dfb9c51b.js": "/js/chunks/a9a0d461dfb9c51b.js",
    "/js/chunks/d26ccf8b85bc3ff4.js": "/js/chunks/d26ccf8b85bc3ff4.js",
    "/js/chunks/d87871feef11758f.js": "/js/chunks/d87871feef11758f.js"
}
